langchain_bytez/BytezChatModel.py
langchain_bytez/BytezLLM.py
langchain_bytez/BytezModelMixin.py
langchain_bytez/BytezStdOutCallbackHandler.py
langchain_bytez/__init__.py
langchain_bytez/test.py
langchain_bytez-0.0.7.dist-info/METADATA
langchain_bytez-0.0.7.dist-info/WHEEL
langchain_bytez-0.0.7.dist-info/top_level.txt
langchain_bytez-0.0.7.dist-info/RECORD
