Metadata-Version: 2.2
Name: langchain_bytez
Version: 0.0.7
Summary: Bytez langchain integration
Home-page: https://github.com/Bytez-com/langchain_bytez
Author: Bytez
Classifier: Development Status :: 4 - Beta
Classifier: Intended Audience :: Developers
Classifier: License :: OSI Approved :: MIT License
Classifier: Programming Language :: Python :: 3
Classifier: Programming Language :: Python :: 3.8
Requires-Dist: langchain==0.3.17
Dynamic: author
Dynamic: classifier
Dynamic: description
Dynamic: description-content-type
Dynamic: home-page
Dynamic: requires-dist
Dynamic: summary
